dense-grownet/__init__.py
dense-grownet/__main__.py
dense-grownet/calculate_metrics.py
dense-grownet/custom_data_loader.py
dense-grownet/custom_linear_layer.py
dense-grownet/custom_loss.py
dense-grownet/dense-grow_net.py
dense-grownet/dense_grow_net.py
dense-grownet/dense_grow_net_base.py
dense-grownet/elastic_net_loss.py
dense-grownet/evaluate_model.py
dense_grownet/__init__.py
dense_grownet/__main__.py
dense_grownet/custom_linear_layer.py
dense_grownet/dense_grow_net.py
dense_grownet/dense_grow_net_base.py
dense_grownet/elastic_net_loss.py
dense_grownet-0.1.7.dist-info/METADATA
dense_grownet-0.1.7.dist-info/WHEEL
dense_grownet-0.1.7.dist-info/top_level.txt
dense_grownet-0.1.7.dist-info/RECORD
