Metadata-Version: 2.1
Name: dense_grownet
Version: 0.1.7
Requires-Dist: torch
Requires-Dist: scikit-learn
